THNet/__init__.py
THNet/load_model.py
THNet/HLA_inference/HLA_inference.py
THNet/HLA_inference/__init__.py
THNet/HLA_inference/model_prediction.py
THNet/HLA_inference/example/input_example.csv
THNet/HLA_inference/models/models_1.pkl
THNet/HLA_inference/models/models_2.pkl
THNet/HLA_inference/parameter/fscore_dict.pkl
THNet/HLA_inference/parameter/hla_auc.pkl
THNet/HLA_inference/parameter/hla_list.pkl
THNet/HLA_inference/parameter/hla_threshold_dict.pkl
THNet/HLA_inference/parameter/v_gene_list.pkl
THNet/Mismatch_score/__init__.py
THNet/Mismatch_score/calculate_MS.py
THNet/Mismatch_score/example/input_example.csv
THNet/Mismatch_score/parameter/class1_distance.pkl
THNet/Mismatch_score/parameter/class2_distance.pkl
THNet/Mismatch_score/parameter/hla_list.pkl
THNet-1.0.3.dist-info/LICENSE
THNet-1.0.3.dist-info/METADATA
THNet-1.0.3.dist-info/WHEEL
THNet-1.0.3.dist-info/entry_points.txt
THNet-1.0.3.dist-info/top_level.txt
THNet-1.0.3.dist-info/RECORD
