Metadata-Version: 2.1
Name: THNet
Version: 1.0.3
Summary: HLA typing based on T-cell beta chain repertoires and HLA mismatch score calculation.
Home-page: https://github.com/Mia-yao/THNet
Author: Mingyao Pan
Author-email: mingyaop@seas.upenn.edu
License: MIT License
Classifier: Development Status :: 3 - Alpha
Classifier: Intended Audience :: Developers
Classifier: Intended Audience :: Healthcare Industry
Classifier: Topic :: Scientific/Engineering :: Bio-Informatics
Classifier: Topic :: Scientific/Engineering :: Medical Science Apps.
Classifier: License :: OSI Approved :: MIT License
Classifier: Natural Language :: English
Classifier: Programming Language :: Python :: 3.11
License-File: LICENSE
Requires-Dist: numpy
Requires-Dist: pandas
Requires-Dist: tqdm
Requires-Dist: scikit-learn
